{
    "status": true,
    "data": {
        "products": [
            {
                "id": "434",
                "name": "Pattern - Fractal Wallpaper",
                "image_url": "https://newevolutiondesigns.com/images/freebies/abstract-background-7.jpg",
		    "image_type":"Love"
            },
            {
                "id": "431",
                "name": "Mickey Mouse",
                "image_url": "http://www.ultrahdfreewallpapers.com/uploads/large/3d-and-abstract/abstract-hd-wallpaper-062.jpg",
		    "image_type":"Hate"
			},
            {
                "id": "431",
                "name": "Mickey Mouse",
                "image_url": "http://www.ultrahdfreewallpapers.com/uploads/large/3d-and-abstract/abstract-hd-wallpaper-062.jpg",
		    "image_type":"Love"
			},
            {
                "id": "431",
                "name": "Mickey Mouse",
                "image_url": "http://www.ultrahdfreewallpapers.com/uploads/large/3d-and-abstract/abstract-hd-wallpaper-062.jpg",
		    "image_type":"Hate"
			},
            {
                "id": "431",
                "name": "Mickey Mouse",
                "image_url": "http://www.ultrahdfreewallpapers.com/uploads/large/3d-and-abstract/abstract-hd-wallpaper-062.jpg",
		    "image_type":"Love"
			},
		{
                "id": "434",
                "name": "Pattern - Fractal Wallpaper",
                "image_url": "https://newevolutiondesigns.com/images/freebies/abstract-background-7.jpg",
		    "image_type":"Life"
            },
            {
                "id": "431",
                "name": "Mickey Mouse",
                "image_url": "http://www.ultrahdfreewallpapers.com/uploads/large/3d-and-abstract/abstract-hd-wallpaper-062.jpg",
		    "image_type":"Love"
			},
            {
                "id": "431",
                "name": "Mickey Mouse",
                "image_url": "http://www.ultrahdfreewallpapers.com/uploads/large/3d-and-abstract/abstract-hd-wallpaper-062.jpg",
		    "image_type":"Hate"
			}
        ]
    }
}
